canonicalwebteam/yaml_responses/__init__.py
canonicalwebteam/yaml_responses/django_helpers.py
canonicalwebteam/yaml_responses/flask_helpers.py
canonicalwebteam.yaml_responses-1.2.0.dist-info/LICENSE.txt
canonicalwebteam.yaml_responses-1.2.0.dist-info/METADATA
canonicalwebteam.yaml_responses-1.2.0.dist-info/WHEEL
canonicalwebteam.yaml_responses-1.2.0.dist-info/top_level.txt
canonicalwebteam.yaml_responses-1.2.0.dist-info/RECORD
